setup.py
docker_registry/__init__.py
docker_registry/../config/config_sinastorage.yml
docker_registry/contrib/__init__.py
docker_registry/contrib/sinastorage/__init__.py
docker_registry/contrib/sinastorage/bucket.py
docker_registry/contrib/sinastorage/multipart.py
docker_registry/contrib/sinastorage/streaming.py
docker_registry/contrib/sinastorage/utils.py
docker_registry/drivers/__init__.py
docker_registry/drivers/sinastorage.py
docker_registry_driver_sinastorage.egg-info/PKG-INFO
docker_registry_driver_sinastorage.egg-info/SOURCES.txt
docker_registry_driver_sinastorage.egg-info/dependency_links.txt
docker_registry_driver_sinastorage.egg-info/namespace_packages.txt
docker_registry_driver_sinastorage.egg-info/requires.txt
docker_registry_driver_sinastorage.egg-info/top_level.txt
docker_registry_driver_sinastorage.egg-info/zip-safe