Metadata-Version: 1.1
Name: docker-registry-driver-sinastorage
Version: 0.1.3
Summary: Docker registry sinastorage driver
Home-page: https://github.com/kerwin/docker-registry-driver-sinastorage
Author: Kerwin Piao
Author-email: piaoyuankui@gmail.com
License: UNKNOWN
Platform: Independent
Classifier: Development Status :: 4 - Beta
Classifier: Intended Audience :: Developers
Classifier: Programming Language :: Python
Classifier: Programming Language :: Python :: 2.7
Classifier: Programming Language :: Python :: Implementation :: CPython
Classifier: Operating System :: OS Independent
Classifier: Topic :: Utilities
